{
    "jp": {
        "mhrhelper": "MHRHelper",
        "name": {
            "鐮鼬龍王": "オサイズチ",
            "青熊獸": "アオアシラ",
            "雌火龍": "リオレイア",
            "泡狐龍": "タマミツネ",
            "河童蛙": "ヨツミワドウ",
            "傘鳥": "アケノシルム",
            "人魚龍": "イソネミクニ",
            "奇怪龍": "フルフル",
            "水獸": "ロアルドロス",
            "火龍": "リオレウス",
            "毒妖鳥": "プケプケ",
            "搔鳥": "クルルヤック",
            "飛雷龍": "トビカガチ",
            "蠻顎龍": "アンジャナフ",
            "泥魚龍": "ジュラトドス",
            "毒狗龍王": "毒狗竜",
            "天狗獸": "ビシュテンゴ",
            "怨虎龍": "マガイマガド",
            "雪鬼獸": "ゴシャハギ",
            "眠狗龍王": "ドスバギィ",
            "白兔獸": "ウルクスス",
            "冰牙龍": "ベリオロス",
            "轟龍": "ティガレックス",
            "土砂龍": "ボルボロス",
            "迅龍": "ナルガクルガ",
            "赤甲獸": "ラングロトラ",
            "岩龍": "バサルモス",
            "雷狼龍": "ジンオウガ",
            "絡新婦": "ヤツカダキ"
        }
    }
}