{
    "jptotw": {
        "ハンターノート": "獵人筆記",
        "ハンターの心得": "獵人心得",
        "大型モンスターリスト": "大型魔物清單",
        "小型モンスターリスト": "小型魔物清單",
        "環境生物リスト": "環境生物清單",
        "手記帳": "筆記本",
        "基本操作指南": "基本操作指南",
        "武器操作指南": "武器操作指南",
        "アルバムメニュー": "相簿選單",
        "取扱説明書": "使用說明書",
        "生態": "生態",
        "部位と肉質": "部位與肉質",
        "状態異常": "狀態異常",
        "素材": "素材",
        "写真の設定": "設定照片",
        "写真の切替": "切換照片",
        "通常": "一般",
        "怒り": "憤怒",
        "過熱状態": "過熱狀態",
        "帯電状態": "帶電狀態",
        "熱殻状態": "熱殼狀態",
        "部位破壊": "破壞部位",
        "満腹状態": "滿腹狀態",
        "超帯電状態": "超帶電狀態",
        "部位破壊後": "破壞部位後",
        "風袋破壊時": "破壞風袋時",
        "泥まとい状態": "泥濘狀態",
        "闘気硬化状態": "鬥氣硬化狀態",
        "龍気解放状態": "龍氣解放狀態",
        "鬼火まとい状態": "鬼火狀態",
        "通常（泡まとい状態）": "一般（泡沫狀態）",
        "怒り（泡まとい状態）": "憤怒（泡沫狀態）",
        "部位破壊（前脚のみ）": "破壞部位（只有前腳）",
        "熱殻状態（部位破壊後）": "熱殼狀態（破壞部位後）",
        "ターゲット": "目標",
        "カッコ内は": "",
        "(破壊後)": "破壞後",
        "(泥纏い時)": "泥纏",
        "(怒り時)": "憤怒時",
        "通常時": "通常",
        "(満腹時)": "滿腹時",
        "(闘気硬化時)": "鬥氣硬化",
        "泥纏い": "泥纏",
        "9にする": "降到0",
        "0にする": "降到0",
        "耐久値を": "耐久值",
        "を": "",
        "と報酬": "報酬",
        "胴体": "身體",
        "尻尾先": "尾尖",
        "ガスだまり": "瓦斯池",
        "尾先": "尾尖",
        "首・背": "頸・背",
        "尾根元": "尾根",
        "回転中": "滾動中",
        "脚(糸)": "腳(絲)",
        "尻先": "尾尖",
        "ビレ": "鰭",
        "片腕": "單腕",
        "片爪": "單爪",
        "片刃翼": "單刃翼",
        "片翼": "單翼",
        "片腕刃": "單腕刃",
        "ブレード": "腕刃",
        "スパイク": "棘",
        "スポンジ": "海綿體",
        "びれ": "鰭",
        "すね": "脛",
        "お腹": "腹",
        "後ろ足": "後腳",
        "後ろ": "後",
        "尾穂先": "尾尖",
        "尾穂": "尾",
        "帯電": "帶電",
        "発電": "發電",
        "泥団子": "大泥球",
        "下位": "初階",
        "上位": "進階",
        "種別": "類別",
        "氷": "冰",
        "海竜種": "海龍種",
        "牙獣種": "牙獸種",
        "牙竜種": "牙龍種",
        "魚竜種": "魚龍種",
        "甲殻種": "甲殼種",
        "甲虫種": "甲蟲種",
        "獣人種": "獸人種",
        "獣竜種": "獸龍種",
        "鳥竜種": "鳥龍種",
        "飛竜種": "飛龍種",
        "古龍種": "古龍種",
        "両生種": "兩生種",
        "鋏角種": "鉗角種",
        "蛇竜種": "蛇龍種",
        "魚類": "魚類",
        "草食種": "草食種",
        "持続強化生物": "持續強化生物",
        "瞬間強化生物": "瞬間強化生物",
        "罠型生物": "陷阱生物",
        "猟具生物": "獵具生物",
        "素材生物": "素材生物",
        "福運生物": "福運生物",
        "希少生物": "稀有生物",
        "その他": "其他",
        "狩猟数（捕獲数）": "狩獵數（捕獲數）",
        "討伐数": "討伐數",
        "危険度": "危險度",
        "最大記録": "最大紀錄",
        "最小記録": "最小紀錄",
        "cm": "cm",
        "開放条件": "開放條件",
        "生息地にいる環境生物に触れることで、\nリストが開放されます。": "可透過接觸棲息於\n當地的環境生物來開放列表。",
        "環境生物を捕まえることで、\nリストが開放されます。": "可透過捕捉環境生物來開放列表。",
        "環境生物を利用することで、\nリストが開放されます。": "可透過使用環境生物來開放列表。",
        "生息地にいる環境生物を撮影することで、\nリストが開放されます。": "可透過拍攝棲息於\n當地的環境生物來開放列表。",
        "環境生物の生息地を訪れることで、\nリストが開放されます。": "可透過前往環境生物\n所在的棲息地來開放列表。",
        "生息地で環境生物を発見することで、\nリストが開放されます。": "可透過在棲息地發現當地的\n環境生物來開放列表。",
        "主な特徴": "主要特徵",
        "主な生息地": "主要棲息地",
        "砂原": "沙原",
        "水没林": "水沒林",
        "大社跡": "大社遺跡",
        "寒冷群島": "寒冷群島",
        "溶岩洞": "熔岩洞",
        "龍宮砦跡": "龍宮要塞遺跡",
        "闘技場": "鬥技場",
        "？？？？": "？？？？",
        "部位": "部位",
        "本体": "身體",
        "脚": "腳",
        "後脚": "後腳",
        "翼脚": "翼腳",
        "前脚": "前腳",
        "脚根本": "大腿根",
        "脚（糸）": "腳（絲）",
        "胸部": "胸部",
        "胸部（帯電）": "胸部（帶電）",
        "胸部（風袋）": "胸部（風袋）",
        "首": "頸",
        "首下": "下頸部",
        "首・背中": "頸･背部",
        "尾刃": "尾刀",
        "尻尾": "尾巴",
        "尻尾下": "尾巴下方",
        "尻尾先端": "尾巴前端",
        "尻尾根本": "尾巴根部",
        "尻尾先端（帯電）": "尾巴前端（帶電）",
        "尻尾先端（風袋）": "尾巴前端（風袋）",
        "尻": "臀",
        "爪": "爪",
        "左爪": "左爪",
        "右爪": "右爪",
        "背中": "背部",
        "背ビレ": "背鰭",
        "背中（帯電）": "背部（帶電）",
        "背中（風袋）": "背部（風袋）",
        "腹部": "腹部",
        "腹部・後脚": "腹部･後腳",
        "腹部（発電器官）": "腹部（發電器官）",
        "腹部（繭化状態）": "腹部（繭化狀態）",
        "腕刃": "腕刃",
        "翼腕": "翼腕",
        "翼腕（帯電）": "翼腕（帶電）",
        "翼腕（風袋）": "翼腕（風袋）",
        "翼": "翅膀",
        "刃翼": "刃翼",
        "ヒレ": "鰭",
        "脚ヒレ": "腳鰭",
        "髪ヒレ": "髮鰭",
        "タテガミ": "鬃毛",
        "角": "角",
        "頭部": "頭部",
        "鼻": "鼻子",
        "舌": "舌頭",
        "体": "軀幹",
        "上半身": "上半身",
        "胴部": "身體",
        "胴": "身體",
        "岩": "岩石",
        "傘": "傘",
        "壺": "壺",
        "棘": "棘",
        "氷塊": "冰塊",
        "大泥玉": "大泥球",
        "全身（回転中）": "全身（旋轉時）",
        "頭殻": "頭殼",
        "クチバシ": "喙",
        "トサカ": "頭冠",
        "皿": "盤子",
        "片角": "單角",
        "両角": "雙角",
        "右腕": "右臂",
        "左腕": "左臂",
        "翼爪": "翼爪",
        "甲羅": "甲殼",
        "灯腹": "燈腹",
        "四脚": "四腳",
        "左脚": "左腳",
        "右脚": "右腳",
        "狩猟指南": "狩獵指南",
        "状態異常の有効度": "狀態異常的有效程度",
        "毒": "毒",
        "麻痺": "麻痺",
        "睡眠": "睡眠",
        "気絶": "昏厥",
        "爆破": "爆破",
        "減気": "減氣",
        "火やられ": "火異常",
        "水やられ": "水異常",
        "氷やられ": "冰異常",
        "雷やられ": "雷異常",
        "★の数や、詳細グラフの量が多いほど、プレイヤーにとって有利です。": "★的數量或詳細圖表內的數字越高，對玩家就越有利。",
        "初回耐性値": "初次耐性值",
        "次回耐性値の上昇量": "下次耐性值的上升量",
        "最大耐性値": "最大耐性值",
        "蓄積値の自然減少量": "累積值的自然減少量",
        "合計ダメージ量": "合計傷害量",
        "効果時間": "效果時間",
        "ダメージ量": "傷害量",
        "スタミナ減少値": "耐力消耗值",
        "ターゲット\n報酬": "目標\n報酬",
        "捕獲\n報酬": "捕獲\n報酬",
        "部位破壊\n報酬": "破壞部位\n報酬",
        "剥ぎ取り\n素材": "剝取\n素材",
        "落とし物": "掉落物",
        "ターゲット報酬": "目標報酬",
        "捕獲報酬": "捕獲報酬",
        "部位破壊報酬": "破壞部位報酬",
        "剥ぎ取り素材": "剝取素材",
        "×": "×",
        "％": "%",
        "ボタンの役割": "按鍵用途",
        "ボタンの役割（斧）": "按鍵用途（斧）",
        "ボタンの役割（剣）": "按鍵用途（劍）",
        "オススメコンボ": "推薦連擊",
        "旋律効果": "旋律效果",
        "大剣": "大劍",
        "太刀": "太刀",
        "片手剣": "單手劍",
        "双剣": "雙劍",
        "ハンマー": "大錘",
        "狩猟笛": "狩獵笛",
        "ランス": "長槍",
        "ガンランス": "銃槍",
        "スラッシュアックス": "斬擊斧",
        "チャージアックス": "充能斧",
        "操虫棍": "操蟲棍",
        "ライトボウガン": "輕弩槍",
        "ヘビィボウガン": "重弩槍",
        "弓": "弓",
        "基本操作": "基本操作",
        "アイテムの使い方": "道具的使用方法",
        "翔蟲を使うアクション": "使用翔蟲的動作",
        "操竜": "操龍",
        "壁を使うアクション": "透過牆壁施展的動作",
        "斬れ味": "銳利度",
        "ハチミツを食べている": "正在吃蜂蜜時",
        "魚を食べている時": "正在吃魚時",
        "音爆弾、閃光玉、罠にかかった時": "音爆彈、閃光彈、陷阱困住時",
        "炎熱蓄積状態中に頭を攻撃してダウン時": "炎熱蓄積狀態中攻擊頭部擊倒時",
        "炎熱蓄積中に頭攻撃してダウン時": "炎熱蓄積狀態中攻擊頭部擊倒時",
        "左右どちらかの脚を破壊": "破壞左腿或右腿",
        "頭または翼の部位破壊時": "頭或翼破壞時",
        "体力30%以下の時に耐久値を1回0にすると報酬": "體力值30%以下時將耐久值1回降到0的報酬",
        "持っている岩や卵を落とした時": "擊落手中的岩石或卵時",
        "音爆弾でダウンさせた時泥纏いを中断させた時攻撃を当てて泳ぎ状態から地上に出した時泥を剥がした時": "當音爆彈擊倒時，當中斷泥纏時，當將他從游泳狀態打回地面時，當剝去泥漿時",
        "音爆弾でダウンさせた時泥纏中断させた時攻撃を当てて泳ぎから地上に出した時泥を剥がした時": "當音爆彈擊倒時，當中斷泥纏時，當將他從游泳狀態打回地面時，當剝去泥漿時",
        "超帯電状態から通常状態に戻った時": "從超帶電恢復到正常狀態時",
        "超帶電から通常に戻った時": "從超帶電恢復到正常狀態時",
        "左右どちらかの爪を破壊": "破壞左爪或右爪",
        "切断属性": "切斷屬性",
        "泡まとい状態の解除時、爪とぎ時": "泡纏狀態解除時",
        "泡まといの解除時、爪とぎ時": "泡纏狀態解除時",
        "突進で地形にぶつかった時音爆弾で怯ませた時": "衝鋒撞到地形時，用音爆彈嚇它時",
        "疲れ状態で突進後にダウンした時": "疲勞狀態下衝鋒倒地",
        "疲れで突進後にダウンした時": "疲勞狀態下衝鋒倒地",
        "左右どちらかの爪の": "左爪或右爪",
        "を引きずって逃げる時": "瘸腿逃跑時",
        "帯電状態を解除させた時張り付いた壁からダメージを受けて落下時": "帶電狀態解除時，在牆上被打下來",
        "帯電解除させた時張り付いた壁からダメージを受けて落下時": "帶電狀態解除時，在牆上被打下來",
        "擬態を解除時": "擬態解除時",
        "食事を中断させた時": "打斷進食時",
        "天井からヨダレを垂らした時": "天花板上流口水時",
        "攻撃に失敗してもがいた時": "攻擊失敗掙扎時",
        "打撃系の攻撃で一定ダメージ": "打撃系的攻擊造成一定傷害",
        "突進で地形にぶつかった時泥を纏った時": "突進撞上地形時，泥纏時。",
        "どちらかの": "任一側",
        "1段階の破壊で報酬": "1次破壞的報酬",
        "2段階の破壊で報酬": "2次破壞的報酬",
        "空中から落下させた時": "空中擊落時",
        "切断系の攻撃": "切斷系(斬)攻擊",
        "タテガミ破壊時": "鬃毛破壞時",
        "剥ぎ取り": "剝取"
    }
}